snakeML/SVM.py
snakeML/__init__.py
snakeML/calibration.py
snakeML/density_estimation.py
snakeML/dimensionality_reduction.py
snakeML/dist.py
snakeML/distance.py
snakeML/fusion.py
snakeML/gaussian.py
snakeML/loads.py
snakeML/logistic_regression.py
snakeML/metrics.py
snakeML/numpy_transformations.py
snakeML/preprocessing.py
snakeML/test.py
snakeML/tunning.py
snakeML/validation.py
snakeML/visualization.py
snakeML-0.0.9.dist-info/METADATA
snakeML-0.0.9.dist-info/WHEEL
snakeML-0.0.9.dist-info/top_level.txt
snakeML-0.0.9.dist-info/RECORD
