Metadata-Version: 2.1
Name: snakeML
Version: 0.0.9
Summary: Machine Learning Library
Author: Manuel Escobar
Author-email: manuelescobar.dev@gmail.com
License: MIT
Keywords: python,ML
Classifier: Development Status :: 3 - Alpha
Classifier: Intended Audience :: Education
Classifier: Programming Language :: Python :: 2
Classifier: Programming Language :: Python :: 3
Classifier: Operating System :: MacOS :: MacOS X
Classifier: Operating System :: Microsoft :: Windows
Requires-Dist: numpy
Requires-Dist: matplotlib
Requires-Dist: sklearn
